LICENSE.txt
MANIFEST.in
Makefile
README.rst
requirements.txt
setup.cfg
setup.py
docs/conf.py
docs/index.rst
docs/license.rst
docs/readme_link.rst
docs/slackapi.rst
docs/tools.rst
docs/_static/sls.png
libslack/__init__.py
libslack/scmd.py
libslack/slackapi.py
libslack/sls.py
libslack/utils.py
libslack/version.py
libslack.egg-info/PKG-INFO
libslack.egg-info/SOURCES.txt
libslack.egg-info/dependency_links.txt
libslack.egg-info/entry_points.txt
libslack.egg-info/requires.txt
libslack.egg-info/top_level.txt
libslack/tests/__init__.py
libslack/tests/scmd_tests.py
libslack/tests/slackapi_tests.py
libslack/tests/sls_tests.py
libslack/tests/utils_tests.py