Metadata-Version: 1.0
Name: libslack
Version: 1.0.0
Summary: A lightweight wrapper around the slack web API.
Home-page: https://github.com/Nicoretti/libslack
Author: Nicola Coretti
Author-email: nico.coretti@gmail.com
License: BSD
Keywords: slack,cmd,api,shell
Platform: UNKNOWN
